jb_payment/__init__.py
jb_payment/payment.py
jb_payment-0.1.5.dist-info/METADATA
jb_payment-0.1.5.dist-info/WHEEL
jb_payment-0.1.5.dist-info/RECORD
