Metadata-Version: 2.1
Name: jb-payment
Version: 0.1.5
Summary: 
Author: Shrey Pandey
Author-email: shreypandey1509@gmail.com
Requires-Python: >=3.11,<4.0
Classifier: Programming Language :: Python :: 3
Classifier: Programming Language :: Python :: 3.11
Classifier: Programming Language :: Python :: 3.12
Requires-Dist: jb-manager-bot (>=0.2.4,<0.3.0)
Requires-Dist: requests (>=2.32.3,<3.0.0)
